likelycause/__init__.py
likelycause/bsuspects.py
likelycause-0.0.4.dist-info/LICENSE.py
likelycause-0.0.4.dist-info/METADATA
likelycause-0.0.4.dist-info/WHEEL
likelycause-0.0.4.dist-info/top_level.txt
likelycause-0.0.4.dist-info/RECORD
